CHANGELOG.rst
MANIFEST.in
README.rst
setup.py
slapos/__init__.py
slapos.extension.strip.egg-info/PKG-INFO
slapos.extension.strip.egg-info/SOURCES.txt
slapos.extension.strip.egg-info/dependency_links.txt
slapos.extension.strip.egg-info/entry_points.txt
slapos.extension.strip.egg-info/namespace_packages.txt
slapos.extension.strip.egg-info/not-zip-safe
slapos.extension.strip.egg-info/requires.txt
slapos.extension.strip.egg-info/top_level.txt
slapos/extension/__init__.py
slapos/extension/strip/__init__.py