Metadata-Version: 1.1
Name: slapos.extension.strip
Version: 0.4
Summary: zc.buildout extension to strip binaries.
Home-page: https://lab.nexedi.com/nexedi/slapos.extension.strip
Author: Kazuhiko Shiozaki
Author-email: kazuhiko@nexedi.com
License: BSD
Keywords: buildout extension strip
Platform: UNKNOWN
Classifier: Framework :: Buildout :: Extension
Classifier: License :: OSI Approved :: BSD License
Classifier: Programming Language :: Python
Classifier: Topic :: Software Development :: Build Tools
